setup.py
Extract.egg-info/PKG-INFO
Extract.egg-info/SOURCES.txt
Extract.egg-info/dependency_links.txt
Extract.egg-info/requires.txt
Extract.egg-info/top_level.txt
Extract.egg-info/zip-safe
extract/__init__.py