Metadata-Version: 1.0
Name: Extract
Version: 1.0
Summary: Extraction tool for model and observed data intercomparison
Home-page: https://bitbucket.org/luizirber/extract
Author: Luiz Irber
Author-email: luiz.irber@gmail.com
License: PSF
Download-URL: https://bitbucket.org/luizirber/extract/downloads
Platform: any
Classifier: Development Status :: 4 - Beta
Classifier: Intended Audience :: Developers
Classifier: Intended Audience :: Science/Research
Classifier: License :: OSI Approved :: Python Software Foundation License
Classifier: Operating System :: OS Independent
Classifier: Programming Language :: Python
Classifier: Programming Language :: Python :: 2
Classifier: Topic :: Scientific/Engineering
Classifier: Topic :: Software Development :: Libraries :: Python Modules
